tap_hubspot/__init__.py
tap_hubspot/auth.py
tap_hubspot/client.py
tap_hubspot/streams.py
tap_hubspot/tap.py
meltano_tap_hubspot-0.7.2.dist-info/LICENSE
meltano_tap_hubspot-0.7.2.dist-info/METADATA
meltano_tap_hubspot-0.7.2.dist-info/WHEEL
meltano_tap_hubspot-0.7.2.dist-info/entry_points.txt
meltano_tap_hubspot-0.7.2.dist-info/RECORD
