Metadata-Version: 2.3
Name: meltano-tap-hubspot
Version: 0.7.2
Summary: Singer tap for tap-hubspot, built with the Meltano Singer SDK.
License: Apache-2.0
Keywords: ELT,tap-hubspot
Author: Ethan Stein
Requires-Python: >=3.10,<4
Classifier: License :: OSI Approved :: Apache Software License
Classifier: Programming Language :: Python :: 3
Classifier: Programming Language :: Python :: 3.10
Classifier: Programming Language :: Python :: 3.11
Classifier: Programming Language :: Python :: 3.12
Classifier: Programming Language :: Python :: 3.13
Provides-Extra: s3
Requires-Dist: backports-datetime-fromisoformat (==2.0.3) ; python_version < "3.11"
Requires-Dist: requests (==2.32.5)
Requires-Dist: s3fs (>=2025.7.0) ; extra == "s3"
Requires-Dist: singer-sdk (>=0.48.0,<0.49.0)
